django_minio_connector/__init__.py
django_minio_connector/storage.py
django_minio_connector-0.0.2.dist-info/METADATA
django_minio_connector-0.0.2.dist-info/WHEEL
django_minio_connector-0.0.2.dist-info/top_level.txt
django_minio_connector-0.0.2.dist-info/RECORD
