Metadata-Version: 2.1
Name: django-minio-connector
Version: 0.0.2
Summary: Django storage backend to use MinIO as file storage. It is wrapper over "minio" library.
Home-page: https://github.com/max-dev-py/django-minio-connector
Author: Maxim Ustinov
Author-email: MaximVUstinovk@gmail.com
License: Apache License 2.0
Keywords: django storage minio
Classifier: Development Status :: 4 - Beta
Classifier: Intended Audience :: Developers
Classifier: License :: OSI Approved :: Apache Software License
Classifier: Programming Language :: Python :: 3.11
Classifier: Environment :: Web Environment
Classifier: Framework :: Django :: 5.1
Classifier: Operating System :: OS Independent
Classifier: Topic :: Software Development :: Libraries :: Python Modules
Requires-Python: >=3.11
Requires-Dist: Django >=5.1
Requires-Dist: minio >=7.2.10
